seevooplay/__init__.py
seevooplay/admin.py
seevooplay/apps.py
seevooplay/forms.py
seevooplay/migrations/0001_initial.py
seevooplay/migrations/__init__.py
seevooplay/models.py
seevooplay/static/seevooplay/css/admin.css
seevooplay/static/seevooplay/css/email_guests.css
seevooplay/static/seevooplay/css/event.css
seevooplay/static/seevooplay/css/resend.css
seevooplay/templates/admin/seevooplay/event/change_form.html
seevooplay/templates/seevooplay/base.html
seevooplay/templates/seevooplay/email_guests.html
seevooplay/templates/seevooplay/email_guests_email.txt
seevooplay/templates/seevooplay/event.html
seevooplay/templates/seevooplay/event_replies.html
seevooplay/templates/seevooplay/invitation_email.txt
seevooplay/templates/seevooplay/reply_notification_email.txt
seevooplay/templates/seevooplay/resend.html
seevooplay/templates/seevooplay/trumbowyg.js
seevooplay/urls.py
seevooplay/utils.py
seevooplay/views.py
seevooplay-1.0.9.dist-info/COPYING
seevooplay-1.0.9.dist-info/METADATA
seevooplay-1.0.9.dist-info/WHEEL
seevooplay-1.0.9.dist-info/RECORD
