Metadata-Version: 2.1
Name: seevooplay
Version: 1.0.9
Summary: Seevooplay is a Django app for online invitations and RSVPs.
Home-page: https://github.com/matthewn/seevooplay
License: GPL-3.0-only
Keywords: django
Author: Matthew Newton
Author-email: matthewn@mahnamahna.net
Requires-Python: >=3.8,<4.0
Classifier: Development Status :: 4 - Beta
Classifier: Environment :: Web Environment
Classifier: Framework :: Django
Classifier: License :: OSI Approved :: GNU General Public License v3 (GPLv3)
Classifier: Operating System :: OS Independent
Classifier: Programming Language :: Python
Classifier: Programming Language :: Python :: 3
Classifier: Programming Language :: Python :: 3.8
Classifier: Programming Language :: Python :: 3.9
Classifier: Programming Language :: Python :: 3.10
Classifier: Programming Language :: Python :: 3.11
Classifier: Programming Language :: Python :: 3.12
Requires-Dist: Django
Requires-Dist: Pillow
Requires-Dist: django-extensions
Requires-Dist: django-model-utils
Requires-Dist: django-richtextfield
Project-URL: Repository, https://github.com/matthewn/seevooplay
